nbapis/__init__.py
nbapis/ctx.py
nbapis/test_ctx.py
nbapis-0.1.21.dist-info/LICENSE
nbapis-0.1.21.dist-info/METADATA
nbapis-0.1.21.dist-info/WHEEL
nbapis-0.1.21.dist-info/top_level.txt
nbapis-0.1.21.dist-info/RECORD
