Metadata-Version: 2.1
Name: nbapis
Version: 0.1.21
Summary: nb api package
Home-page: UNKNOWN
Author: zhchangAuthor
Author-email: chang@nextbillion.ai
License: UNKNOWN
Platform: UNKNOWN
Classifier: Programming Language :: Python :: 3
Classifier: License :: OSI Approved :: MIT License
Classifier: Operating System :: OS Independent
Requires-Python: >=3.6
Requires-Dist: fastapi (>=0.53.2)
